pyastroschema/VERSION
pyastroschema/__init__.py
pyastroschema/__main__.py
pyastroschema/keys.py
pyastroschema/schema.py
pyastroschema/struct.py
pyastroschema/utils.py
pyastroschema/validation.py
pyastroschema-0.5.4.dist-info/METADATA
pyastroschema-0.5.4.dist-info/RECORD
pyastroschema-0.5.4.dist-info/WHEEL
pyastroschema-0.5.4.dist-info/top_level.txt
