Metadata-Version: 2.1
Name: pyastroschema
Version: 0.5.4
Summary: Standardized specifications for astronomy and astrophysics data.
Home-page: https://github.com/astrocatalogs/astroschema
Author: Luke Zoltan Kelley
Author-email: lzkelley@gmail.com
License: GNU
Platform: UNKNOWN
Classifier: Programming Language :: Python :: 3
Classifier: Programming Language :: Python :: 2
Classifier: Operating System :: OS Independent
